nafas/__init__.py
nafas/__main__.py
nafas/functions.py
nafas/params.py
nafas/sounds/silence.wav
nafas/sounds/au1/exhale.wav
nafas/sounds/au1/inhale.wav
nafas/sounds/au1/preparing.wav
nafas/sounds/au1/retain.wav
nafas/sounds/au1/start.wav
nafas/sounds/au1/sustain.wav
nafas/sounds/au1/well_done.wav
nafas/sounds/au2/exhale.wav
nafas/sounds/au2/inhale.wav
nafas/sounds/au2/preparing.wav
nafas/sounds/au2/retain.wav
nafas/sounds/au2/start.wav
nafas/sounds/au2/sustain.wav
nafas/sounds/au2/well_done.wav
nafas/sounds/ca1/exhale.wav
nafas/sounds/ca1/inhale.wav
nafas/sounds/ca1/preparing.wav
nafas/sounds/ca1/retain.wav
nafas/sounds/ca1/start.wav
nafas/sounds/ca1/sustain.wav
nafas/sounds/ca1/well_done.wav
nafas/sounds/ca2/exhale.wav
nafas/sounds/ca2/inhale.wav
nafas/sounds/ca2/preparing.wav
nafas/sounds/ca2/retain.wav
nafas/sounds/ca2/start.wav
nafas/sounds/ca2/sustain.wav
nafas/sounds/ca2/well_done.wav
nafas/sounds/cn1/exhale.wav
nafas/sounds/cn1/inhale.wav
nafas/sounds/cn1/preparing.wav
nafas/sounds/cn1/retain.wav
nafas/sounds/cn1/start.wav
nafas/sounds/cn1/sustain.wav
nafas/sounds/cn1/well_done.wav
nafas/sounds/cn2/exhale.wav
nafas/sounds/cn2/inhale.wav
nafas/sounds/cn2/preparing.wav
nafas/sounds/cn2/retain.wav
nafas/sounds/cn2/start.wav
nafas/sounds/cn2/sustain.wav
nafas/sounds/cn2/well_done.wav
nafas/sounds/in1/exhale.wav
nafas/sounds/in1/inhale.wav
nafas/sounds/in1/preparing.wav
nafas/sounds/in1/retain.wav
nafas/sounds/in1/start.wav
nafas/sounds/in1/sustain.wav
nafas/sounds/in1/well_done.wav
nafas/sounds/in2/exhale.wav
nafas/sounds/in2/inhale.wav
nafas/sounds/in2/preparing.wav
nafas/sounds/in2/retain.wav
nafas/sounds/in2/start.wav
nafas/sounds/in2/sustain.wav
nafas/sounds/in2/well_done.wav
nafas/sounds/uk1/exhale.wav
nafas/sounds/uk1/inhale.wav
nafas/sounds/uk1/preparing.wav
nafas/sounds/uk1/retain.wav
nafas/sounds/uk1/start.wav
nafas/sounds/uk1/sustain.wav
nafas/sounds/uk1/well_done.wav
nafas/sounds/uk2/exhale.wav
nafas/sounds/uk2/inhale.wav
nafas-1.4.dist-info/licenses/AUTHORS.md
nafas-1.4.dist-info/licenses/LICENSE
nafas-1.4.dist-info/METADATA
nafas-1.4.dist-info/WHEEL
nafas-1.4.dist-info/entry_points.txt
nafas-1.4.dist-info/top_level.txt
nafas-1.4.dist-info/RECORD
