Metadata-Version: 2.4
Name: nafas
Version: 1.4
Summary: Breathing gymnastics application
Home-page: https://github.com/sepandhaghighi/nafas
Download-URL: https://github.com/sepandhaghighi/nafas/tarball/v1.4
Author: Nafas Development Team
Author-email: me@sepand.tech
License: MIT
Project-URL: Source, https://github.com/sepandhaghighi/nafas
Project-URL: Discord, https://discord.gg/CtZUNKJHP4
Keywords: breath breathing meditation yoga pranayama
Classifier: Development Status :: 5 - Production/Stable
Classifier: Natural Language :: English
Classifier: License :: OSI Approved :: MIT License
Classifier: Operating System :: OS Independent
Classifier: Programming Language :: Python :: 3.7
Classifier: Programming Language :: Python :: 3.8
Classifier: Programming Language :: Python :: 3.9
Classifier: Programming Language :: Python :: 3.10
Classifier: Programming Language :: Python :: 3.11
Classifier: Programming Language :: Python :: 3.12
Classifier: Programming Language :: Python :: 3.13
Classifier: Intended Audience :: Developers
Classifier: Intended Audience :: Education
Classifier: Intended Audience :: End Users/Desktop
Classifier: Intended Audience :: Other Audience
Classifier: Topic :: Games/Entertainment
Classifier: Topic :: Utilities
Requires-Python: >=3.7
License-File: LICENSE
License-File: AUTHORS.md
Requires-Dist: art>=1.8
Requires-Dist: nava>=0.4
Dynamic: author
Dynamic: author-email
Dynamic: classifier
Dynamic: description
Dynamic: description-content-type
Dynamic: download-url
Dynamic: home-page
Dynamic: keywords
Dynamic: license
Dynamic: license-file
Dynamic: project-url
Dynamic: requires-dist
Dynamic: requires-python
Dynamic: summary
